<?xml version="1.0" encoding="UTF-8"?>
<objects serializationModel="Studio.01.10.00">
    <object class="Event" id="{1e228443-d256-43e6-9ed8-102aad8e96ed}">
        <property name="name">
            <value>Music</value>
        </property>
        <property name="outputFormat">
            <value>1</value>
        </property>
        <relationship name="folder">
            <destination>{d4327fc9-70ce-431b-b544-6d066849914e}</destination>
        </relationship>
        <relationship name="mixer">
            <destination>{87089ea1-191e-4e64-912c-38cbcfc8c820}</destination>
        </relationship>
        <relationship name="masterTrack">
            <destination>{9d116ed0-8e01-44d7-b398-4d39c6cf6668}</destination>
        </relationship>
        <relationship name="mixerInput">
            <destination>{04df7f86-e2f3-4b9b-8b22-cf0b46f7f33b}</destination>
        </relationship>
        <relationship name="automatableProperties">
            <destination>{113680ac-009c-41ce-a06e-ccc334466751}</destination>
        </relationship>
        <relationship name="markerTracks">
            <destination>{941aa462-f955-4340-bb84-a209c13b4aea}</destination>
        </relationship>
        <relationship name="groupTracks">
            <destination>{036dfb2c-bbc7-49f3-a25d-36fdc692da5d}</destination>
            <destination>{4d7c7983-2299-4027-b3eb-e88f34de93a2}</destination>
        </relationship>
        <relationship name="timeline">
            <destination>{590f5b7b-7d4b-4d6b-8fbb-8614ed26d71c}</destination>
        </relationship>
        <relationship name="parameters">
            <destination>{572e6b6b-1b63-451b-b988-452676dbdd3b}</destination>
        </relationship>
    </object>
    <object class="EventMixer" id="{87089ea1-191e-4e64-912c-38cbcfc8c820}">
        <relationship name="masterBus">
            <destination>{286572e3-471f-4e84-abad-8f1c87c7d08d}</destination>
        </relationship>
    </object>
    <object class="MasterTrack" id="{9d116ed0-8e01-44d7-b398-4d39c6cf6668}">
        <relationship name="mixerGroup">
            <destination>{286572e3-471f-4e84-abad-8f1c87c7d08d}</destination>
        </relationship>
    </object>
    <object class="MixerInput" id="{04df7f86-e2f3-4b9b-8b22-cf0b46f7f33b}">
        <relationship name="effectChain">
            <destination>{12ffc6dc-dc58-4875-a645-58409351bba4}</destination>
        </relationship>
        <relationship name="panner">
            <destination>{6a5a6462-9a46-4d54-ae87-c34e4d7a457c}</destination>
        </relationship>
        <relationship name="output">
            <destination>{a217092f-11b6-4c83-ba87-6f5b752cfbff}</destination>
        </relationship>
    </object>
    <object class="EventAutomatableProperties" id="{113680ac-009c-41ce-a06e-ccc334466751}"/>
    <object class="MarkerTrack" id="{941aa462-f955-4340-bb84-a209c13b4aea}"/>
    <object class="GroupTrack" id="{036dfb2c-bbc7-49f3-a25d-36fdc692da5d}">
        <relationship name="modules">
            <destination>{375d22fe-c629-479a-b41c-ce7f252adb61}</destination>
            <destination>{608eed53-939f-454b-96d9-d14a623891db}</destination>
            <destination>{13f108e6-677a-48be-b5cb-cd551e7aa2a0}</destination>
            <destination>{53bd6d9b-ff33-4b0d-8244-5886b6c4f759}</destination>
        </relationship>
        <relationship name="mixerGroup">
            <destination>{4b24522e-f6f2-4536-9160-74d0ecd1f21b}</destination>
        </relationship>
    </object>
    <object class="GroupTrack" id="{4d7c7983-2299-4027-b3eb-e88f34de93a2}">
        <relationship name="mixerGroup">
            <destination>{cbcdd36d-ff2e-4581-9c45-d4eeca766bd7}</destination>
        </relationship>
    </object>
    <object class="Timeline" id="{590f5b7b-7d4b-4d6b-8fbb-8614ed26d71c}">
        <relationship name="modules">
            <destination>{13f108e6-677a-48be-b5cb-cd551e7aa2a0}</destination>
            <destination>{375d22fe-c629-479a-b41c-ce7f252adb61}</destination>
            <destination>{608eed53-939f-454b-96d9-d14a623891db}</destination>
            <destination>{53bd6d9b-ff33-4b0d-8244-5886b6c4f759}</destination>
        </relationship>
        <relationship name="markers">
            <destination>{4d8e0c80-33f7-4c51-a1f5-aa5ef69a1f99}</destination>
            <destination>{9dcf09aa-7380-44b2-9a6b-1862b0d12ba8}</destination>
            <destination>{3b391656-94af-4463-9205-c421f98ddb8f}</destination>
        </relationship>
    </object>
    <object class="ParameterProxy" id="{572e6b6b-1b63-451b-b988-452676dbdd3b}">
        <relationship name="preset">
            <destination>{d92b8519-7498-4084-a4ec-4334c1ee2a31}</destination>
        </relationship>
    </object>
    <object class="EventMixerMaster" id="{286572e3-471f-4e84-abad-8f1c87c7d08d}">
        <relationship name="effectChain">
            <destination>{9e72d11a-91f7-476c-835e-a737a7ed4499}</destination>
        </relationship>
        <relationship name="panner">
            <destination>{da07225f-7513-4a42-ad64-2b9514395b70}</destination>
        </relationship>
        <relationship name="mixer">
            <destination>{87089ea1-191e-4e64-912c-38cbcfc8c820}</destination>
        </relationship>
    </object>
    <object class="MixerBusEffectChain" id="{12ffc6dc-dc58-4875-a645-58409351bba4}">
        <relationship name="effects">
            <destination>{6de27f49-feeb-466f-99b6-dd0ffb0c8f77}</destination>
        </relationship>
    </object>
    <object class="MixerBusPanner" id="{6a5a6462-9a46-4d54-ae87-c34e4d7a457c}"/>
    <object class="SingleSound" id="{375d22fe-c629-479a-b41c-ce7f252adb61}">
        <property name="start">
            <value>19.981383165414417</value>
        </property>
        <property name="length">
            <value>8.3478458049886619</value>
        </property>
        <relationship name="audioFile">
            <destination>{6b0f6fa7-daf1-49d1-9fa8-2f6c519147c9}</destination>
        </relationship>
    </object>
    <object class="SingleSound" id="{608eed53-939f-454b-96d9-d14a623891db}">
        <property name="start">
            <value>28.329228970403079</value>
        </property>
        <property name="length">
            <value>8.3478458049886619</value>
        </property>
        <relationship name="audioFile">
            <destination>{0d670734-63db-4ba3-9df2-746570c1f7bd}</destination>
        </relationship>
    </object>
    <object class="SingleSound" id="{13f108e6-677a-48be-b5cb-cd551e7aa2a0}">
        <property name="start">
            <value>7.4610280394625299</value>
        </property>
        <property name="length">
            <value>12</value>
        </property>
        <relationship name="audioFile">
            <destination>{b85326ec-25ca-444d-b8b1-d2cc60e6aeec}</destination>
        </relationship>
    </object>
    <object class="SingleSound" id="{53bd6d9b-ff33-4b0d-8244-5886b6c4f759}">
        <property name="length">
            <value>6.8571428571428568</value>
        </property>
        <relationship name="audioFile">
            <destination>{b2bbc5d3-f253-4b34-919f-6a891a394cd4}</destination>
        </relationship>
    </object>
    <object class="EventMixerGroup" id="{4b24522e-f6f2-4536-9160-74d0ecd1f21b}">
        <property name="name">
            <value>Piano</value>
        </property>
        <relationship name="effectChain">
            <destination>{2f67f007-9292-47d9-9394-2c577dabb14d}</destination>
        </relationship>
        <relationship name="panner">
            <destination>{60431dea-3196-4bf4-bc24-92b230c14295}</destination>
        </relationship>
        <relationship name="output">
            <destination>{286572e3-471f-4e84-abad-8f1c87c7d08d}</destination>
        </relationship>
    </object>
    <object class="EventMixerGroup" id="{cbcdd36d-ff2e-4581-9c45-d4eeca766bd7}">
        <property name="volume">
            <value>-4.5</value>
        </property>
        <property name="name">
            <value>Audio 1</value>
        </property>
        <relationship name="effectChain">
            <destination>{4dd3662d-2964-4e8e-8bb3-c465835b36ba}</destination>
        </relationship>
        <relationship name="panner">
            <destination>{ecaf845e-d85b-4f71-9ba9-3e01225bf583}</destination>
        </relationship>
        <relationship name="output">
            <destination>{286572e3-471f-4e84-abad-8f1c87c7d08d}</destination>
        </relationship>
    </object>
    <object class="LoopRegion" id="{4d8e0c80-33f7-4c51-a1f5-aa5ef69a1f99}">
        <property name="position">
            <value>7.4610280394625299</value>
        </property>
        <property name="length">
            <value>12</value>
        </property>
        <relationship name="timeline">
            <destination>{590f5b7b-7d4b-4d6b-8fbb-8614ed26d71c}</destination>
        </relationship>
        <relationship name="markerTrack">
            <destination>{941aa462-f955-4340-bb84-a209c13b4aea}</destination>
        </relationship>
    </object>
    <object class="LoopRegion" id="{9dcf09aa-7380-44b2-9a6b-1862b0d12ba8}">
        <property name="position">
            <value>19.981383165414417</value>
        </property>
        <property name="length">
            <value>16.695691609977331</value>
        </property>
        <relationship name="timeline">
            <destination>{590f5b7b-7d4b-4d6b-8fbb-8614ed26d71c}</destination>
        </relationship>
        <relationship name="markerTrack">
            <destination>{941aa462-f955-4340-bb84-a209c13b4aea}</destination>
        </relationship>
    </object>
    <object class="LoopRegion" id="{3b391656-94af-4463-9205-c421f98ddb8f}">
        <property name="position">
            <value>0</value>
        </property>
        <property name="length">
            <value>6.8571428571428568</value>
        </property>
        <relationship name="timeline">
            <destination>{590f5b7b-7d4b-4d6b-8fbb-8614ed26d71c}</destination>
        </relationship>
        <relationship name="markerTrack">
            <destination>{941aa462-f955-4340-bb84-a209c13b4aea}</destination>
        </relationship>
    </object>
    <object class="MixerBusEffectChain" id="{9e72d11a-91f7-476c-835e-a737a7ed4499}">
        <relationship name="effects">
            <destination>{a8a2fe17-715f-4593-8312-532538527bad}</destination>
        </relationship>
    </object>
    <object class="MixerBusPanner" id="{da07225f-7513-4a42-ad64-2b9514395b70}"/>
    <object class="MixerBusFader" id="{6de27f49-feeb-466f-99b6-dd0ffb0c8f77}"/>
    <object class="MixerBusEffectChain" id="{2f67f007-9292-47d9-9394-2c577dabb14d}">
        <relationship name="effects">
            <destination>{ed6d7ad9-ce8b-48e0-ba35-a40ba5d5e1b9}</destination>
        </relationship>
    </object>
    <object class="MixerBusPanner" id="{60431dea-3196-4bf4-bc24-92b230c14295}"/>
    <object class="MixerBusEffectChain" id="{4dd3662d-2964-4e8e-8bb3-c465835b36ba}">
        <relationship name="effects">
            <destination>{56ce4628-5f8f-4ced-91a3-072481083df6}</destination>
        </relationship>
    </object>
    <object class="MixerBusPanner" id="{ecaf845e-d85b-4f71-9ba9-3e01225bf583}"/>
    <object class="MixerBusFader" id="{a8a2fe17-715f-4593-8312-532538527bad}"/>
    <object class="MixerBusFader" id="{ed6d7ad9-ce8b-48e0-ba35-a40ba5d5e1b9}"/>
    <object class="MixerBusFader" id="{56ce4628-5f8f-4ced-91a3-072481083df6}"/>
</objects>
